{
    "transitions": [
        {
            "handler": "de.freewarepoint.whohasmystuff.ListLentObjects/boolean onOptionsItemSelected(android.view.MenuItem)",
            "sources": [
                "de.freewarepoint.whohasmystuff.ListLentObjects"
            ],
            "targets": [
                "de.freewarepoint.whohasmystuff.ShowHistory"
            ]
        },
        {
            "handler": "de.freewarepoint.whohasmystuff.ListLentObjects/boolean onOptionsItemSelected(android.view.MenuItem)",
            "sources": [
                "de.freewarepoint.whohasmystuff.ListLentObjects"
            ],
            "targets": [
                "de.freewarepoint.whohasmystuff.AddObject"
            ]
        }
    ]
}